{"is_source_file": true, "format": "JavaScript", "description": "Main application setup for the user authentication backend, defining middlewares, database connection, API documentation, and route mounting.", "external_files": ["./routes", "../swagger", "./services/database"], "external_methods": ["database.connect()", "swaggerUi.serve", "swaggerUi.setup()"], "published": ["app"], "classes": [], "methods": [{"name": "connect", "description": "Connects to the database (defined in ./services/database)"}], "calls": ["require('dotenv').config()", "const cors = require('cors')", "const express = require('express')", "const routes = require('./routes')", "const swaggerUi = require('swagger-ui-express')", "const swaggerSpec = require('../swagger')", "const database = require('./services/database')", "database.connect()", "app.use(cors({...}))", "app.set('trust proxy', true)", "app.use('/docs', swaggerUi.serve, ...)", "swaggerUi.setup(dynamicSpec)(req, res, next)", "app.use(express.json())", "app.use('/', routes)", "app.use((err, req, res, next) => {...})"], "search-terms": ["app.js", "Express setup", "Swagger integration", "Database connection", "CORS configuration", "Error handling middleware"], "state": 2, "file_id": 8, "knowledge_revision": 47, "git_revision": "55ca0040d3bcc48bb9f21707b74c96a20385ec8a", "revision_history": [{"21": "6364ea96aff73c90b15b1d27ca5cf5d6bbf435b8"}, {"42": "6364ea96aff73c90b15b1d27ca5cf5d6bbf435b8"}, {"46": "6364ea96aff73c90b15b1d27ca5cf5d6bbf435b8"}, {"47": "55ca0040d3bcc48bb9f21707b74c96a20385ec8a"}], "ctags": [{"_type": "tag", "name": "app", "path": "/home/kavia/workspace/code-generation/secure-user-authentication-service-32e9faf8/user_auth_backend/src/app.js", "pattern": "/^const app = express();$/", "language": "JavaScript", "kind": "constant"}, {"_type": "tag", "name": "cors", "path": "/home/kavia/workspace/code-generation/secure-user-authentication-service-32e9faf8/user_auth_backend/src/app.js", "pattern": "/^const cors = require('cors');$/", "language": "JavaScript", "kind": "constant"}, {"_type": "tag", "name": "database", "path": "/home/kavia/workspace/code-generation/secure-user-authentication-service-32e9faf8/user_auth_backend/src/app.js", "pattern": "/^const database = require('.\\/services\\/database');$/", "language": "JavaScript", "kind": "constant"}, {"_type": "tag", "name": "express", "path": "/home/kavia/workspace/code-generation/secure-user-authentication-service-32e9faf8/user_auth_backend/src/app.js", "pattern": "/^const express = require('express');$/", "language": "JavaScript", "kind": "constant"}, {"_type": "tag", "name": "routes", "path": "/home/kavia/workspace/code-generation/secure-user-authentication-service-32e9faf8/user_auth_backend/src/app.js", "pattern": "/^const routes = require('.\\/routes');$/", "language": "JavaScript", "kind": "constant"}, {"_type": "tag", "name": "swaggerSpec", "path": "/home/kavia/workspace/code-generation/secure-user-authentication-service-32e9faf8/user_auth_backend/src/app.js", "pattern": "/^const swaggerSpec = require('..\\/swagger');$/", "language": "JavaScript", "kind": "constant"}, {"_type": "tag", "name": "swaggerUi", "path": "/home/kavia/workspace/code-generation/secure-user-authentication-service-32e9faf8/user_auth_backend/src/app.js", "pattern": "/^const swaggerUi = require('swagger-ui-express');$/", "language": "JavaScript", "kind": "constant"}], "hash": "4b1185b350eb6bdd21042e019dc5cee1", "format-version": 4, "code-base-name": "user_auth_backend", "filename": "user_auth_backend/src/app.js"}